{
  "default": {
    "flavor_preference": "無",
    "recipe_type_preference": "無",
    "avoid_ingredients": "無",
    "cooking_constraints": "無",
    "dietary_restrictions": "無"
  },
  "Apollo": {
    "user_id": "Apollo",
    "flavor_preference": "無",
    "recipe_type_preference": "無",
    "avoid_ingredients": "無",
    "cooking_constraints": "無",
    "dietary_restrictions": "無"
  },
  "tuna": {
    "flavor_preference": "中式",
    "recipe_type_preference": "無",
    "avoid_ingredients": "香菜",
    "cooking_constraints": "無",
    "dietary_restrictions": "無"
  },
  "test": {
    "user_id": "test",
    "flavor_preference": "無",
    "recipe_type_preference": "法式",
    "avoid_ingredients": "雞蛋",
    "cooking_constraints": "無",
    "dietary_restrictions": "無"
  },
  "Harry": {
    "flavor_preference": "無",
    "recipe_type_preference": "台式",
    "avoid_ingredients": "無",
    "cooking_constraints": "無",
    "dietary_restrictions": "無"
  }
}